[
  {
    "id_vehiculo": 1,
    "patente": "ABC123",
    "marca": "Toyota",
    "modelo": "Corolla",
    "tipo": "Sedan",
    "año": 2015,
    "kilometraje": 75000,
    "precio_compra": 12000,
    "precio_venta": 15000,
    "estado": "Disponible"
  },
  {
    "id_vehiculo": 2,
    "patente": "Dby640",
    "marca": "Chevrolet",
    "modelo": "Corsa",
    "tipo": "Sedan",
    "año": 2024,
    "kilometraje": 13000,
    "precio_compra": "100000",
    "precio_venta": "210000",
    "estado": "Disponible"
  },
  {
    "id_vehiculo": 3,
    "patente": "BVA132",
    "marca": "Volkswagen",
    "modelo": "Gol",
    "tipo": "Nose",
    "año": 2019,
    "kilometraje": 30000,
    "precio_compra": 7000000.0,
    "precio_venta": 8232900.0,
    "estado": "Reservado"
  },
  {
    "id_vehiculo": 4,
    "patente": "KLJ321",
    "marca": "Ford",
    "modelo": "Ranger",
    "tipo": "Pickup",
    "año": 2000,
    "kilometraje": 38777,
    "precio_compra": 1900.0,
    "precio_venta": 3212.32,
    "estado": "Vendido"
  },
  {
    "id_vehiculo": 6,
    "patente": "ASDF",
    "marca": "Lkj",
    "modelo": "Lkj",
    "tipo": "Lkj",
    "año": 123,
    "kilometraje": 123,
    "precio_compra": 213.0,
    "precio_venta": 1231.0,
    "estado": "Disponible"
  },
  {
    "id_vehiculo": 7,
    "patente": "DBY640",
    "marca": "Chevrolet",
    "modelo": "Corsa",
    "tipo": "Sedan",
    "año": 2000,
    "kilometraje": 174993,
    "precio_compra": 700000.0,
    "precio_venta": 1344321.0,
    "estado": "Disponible"
  },
  {
    "id_vehiculo": 8,
    "patente": "FSA534",
    "marca": "Ford",
    "modelo": "Escort",
    "tipo": "Hatchback",
    "año": 2009,
    "kilometraje": 2131231,
    "precio_compra": 1231234.0,
    "precio_venta": 312313.0,
    "estado": "Reservado"
  },
  {
    "id_vehiculo": 9,
    "patente": "AB321SF",
    "marca": "Peugeot",
    "modelo": "308",
    "tipo": "Sedan",
    "año": 2004,
    "kilometraje": 2342,
    "precio_compra": 2342344.0,
    "precio_venta": 3242342.0,
    "estado": "Disponible"
  },
  {
    "id_vehiculo": 10,
    "patente": "ÑÑÑ123",
    "marca": "Fiat",
    "modelo": "Chronos",
    "tipo": "Sedan",
    "año": 2020,
    "kilometraje": 2314,
    "precio_compra": 42342.0,
    "precio_venta": 42342.0,
    "estado": "Disponible"
  },
  {
    "id_vehiculo": 11,
    "patente": "ADSFAD",
    "marca": "Asdfad",
    "modelo": "Adfasfd",
    "tipo": "Asdfasd",
    "año": 123123,
    "kilometraje": 21313,
    "precio_compra": 2312312.0,
    "precio_venta": 31231.0,
    "estado": "Disponible"
  },
  {
    "id_vehiculo": 13,
    "patente": "XX 123 XX",
    "marca": "Asdfa",
    "modelo": "Asdfasd",
    "tipo": "Asdfas",
    "año": 1231,
    "kilometraje": 12312,
    "precio_compra": 3123.0,
    "precio_venta": 213.0,
    "estado": "Disponible"
  },
  {
    "id_vehiculo": 14,
    "patente": "XXX 123",
    "marca": "Asdfasd",
    "modelo": "Asdfasdf",
    "tipo": "Asfasdfa",
    "año": 123123,
    "kilometraje": 12312,
    "precio_compra": 312312.0,
    "precio_venta": 312.0,
    "estado": "Disponible"
  },
  {
    "id_vehiculo": 15,
    "patente": "AA342FD",
    "marca": "Afasdfas",
    "modelo": "Dafsda",
    "tipo": "Asdfasd",
    "año": 123123,
    "kilometraje": 123123,
    "precio_compra": 12312.0,
    "precio_venta": 12312.0,
    "estado": "Disponible"
  },
  {
    "id_vehiculo": 16,
    "patente": "XXX123",
    "marca": "Asdasdf",
    "modelo": "Asdfa",
    "tipo": "Asdf",
    "año": 1231,
    "kilometraje": 12312,
    "precio_compra": 123.0,
    "precio_venta": 23123.0,
    "estado": "Disponible"
  },
  {
    "id_vehiculo": 17,
    "patente": "AB 123 FD",
    "marca": "Marca",
    "modelo": "Modelo",
    "tipo": "Tipo",
    "año": 2044,
    "kilometraje": 300000,
    "precio_compra": 43000.0,
    "precio_venta": 43242.0,
    "estado": "Reservado"
  },
  {
    "id_vehiculo": 18,
    "patente": "ASD123",
    "marca": "Marca",
    "modelo": "Modelo",
    "tipo": "Tipo",
    "año": 13,
    "kilometraje": 312,
    "precio_compra": 123.0,
    "precio_venta": 312.0,
    "estado": "Disponible"
  },
  {
    "id_vehiculo": 19,
    "patente": "ASD124",
    "marca": "1231",
    "modelo": "1231",
    "tipo": "3124",
    "año": 23123,
    "kilometraje": 123,
    "precio_compra": 1213.0,
    "precio_venta": 231312.0,
    "estado": "Disponible"
  }
]